MANIFEST.in
README.md
setup.py
gradient_optimizers/__init__.py
gradient_optimizers/gradient_hf_model.py
gradient_optimizers/gradient_model.py
gradient_optimizers.egg-info/PKG-INFO
gradient_optimizers.egg-info/SOURCES.txt
gradient_optimizers.egg-info/dependency_links.txt
gradient_optimizers.egg-info/not-zip-safe
gradient_optimizers.egg-info/requires.txt
gradient_optimizers.egg-info/top_level.txt
gradient_optimizers/utils/__init__.py
gradient_optimizers/utils/nnet.py
gradient_optimizers/utils/nnet_named.py