Metadata-Version: 1.1
Name: gradient-optimizers
Version: 0.0.2
Summary: Python package for wrapping gradient optimizers for models in Theano
Home-page: https://github.com/JonathanRaiman/gradient_optimizers
Author: Jonathan Raiman
Author-email: jraiman at mit dot edu
License: MIT
Download-URL: https://github.com/JonathanRaiman/gradient_optimizers
Keywords: Machine Learning,Gradient Descent,NLP,Optimization,Hessian Free optimization
Platform: any
Classifier: Intended Audience :: Science/Research
Classifier: Operating System :: OS Independent
Classifier: Programming Language :: Python :: 3.3
Classifier: Topic :: Text Processing :: Linguistic
Classifier: Topic :: Scientific/Engineering :: Artificial Intelligence
Classifier: Topic :: Scientific/Engineering :: Mathematics
